enguard/__init__.py
enguard-0.1.1.dist-info/METADATA
enguard-0.1.1.dist-info/WHEEL
enguard-0.1.1.dist-info/top_level.txt
enguard-0.1.1.dist-info/RECORD
