Metadata-Version: 2.4
Name: enguard
Version: 0.1.1
Summary: One guardrail for all, all guardrails for one!
Requires-Python: <3.14,>=3.9
Requires-Dist: litellm
Requires-Dist: model2vec>=0.5.0
Requires-Dist: sentence-transformers>=4.1.0
Requires-Dist: torch>=2.7.0
Requires-Dist: transformers>=4.52.3
